Workbook
Name CBH: #REF!
Name COUNTRY: #REF!
Name exch: #REF!
Name EXCHCODE: #REF!
Name ISO: #REF!
Name mic: #REF!

Sheet Worksheet Raw
A1: Ticker | B1: Name | C1: Weight | D1: Shares | E1: Price
A2: NVDA UW Equity | B2: NVIDIA Corp | C2: 4.597839 | D2: 23276.336 | E2: 239.24
A3: AAPL UW Equity | B3: Apple Inc | C3: 3.964919 | D3: 14393.417 | E3: 333.63
A4: MSFT UW Equity | B4: Microsoft Corp | C4: 3.244055 | D4: 7423.026 | E4: 529.3
A5: AMZN UW Equity | B5: Amazon.com Inc | C5: 2.088672 | D5: 9870.364 | E5: 256.29
A6: GOOGL UW Equity | B6: Alphabet Inc | C6: 1.66471 | D6: 5799.004 | E6: 347.68
A7: 2330 TT Equity | B7: Taiwan Semiconductor Manufactu | C7: 1.598681 | D7: 23883.389 | E7: 2585
A8: AVGO UW Equity | B8: Broadcom Inc | C8: 1.449213 | D8: 4670.448 | E8: 375.81
A9: GOOG UW Equity | B9: Alphabet Inc | C9: 1.350542 | D9: 4746.79 | E9: 344.59
A10: META UW Equity | B10: Meta Platforms Inc | C10: 1.338672 | D10: 2194.294 | E10: 738.88
A11: TSLA UW Equity | B11: Tesla Inc | C11: 1.110504 | D11: 3533.091 | E11: 380.68
A12: MU UW Equity | B12: Micron Technology Inc | C12: 0.972658 | D12: 1126.694 | E12: 1045.56
A13: AMD UW Equity | B13: Advanced Micro Devices Inc | C13: 0.871129 | D13: 1624.619 | E13: 649.42
... A10421: AXG UR Equity | B10421: Solowin Holdings | C10421: 6e-06 | D10421: 62.5 | E10421: 0.112

Sheet Worksheet Final
A1: Bloomberg Title | B1: Ticker | C1: Exchange Code | D1: Equity Exchange Name | E1: MIC | F1: Operating MIC | G1: MIC Exchange Name | H1: Security Type | I1: Name | J1: ISO Country | K1: Weight | L1: Shares | M1: Price
A2: NVDA UW Equity | B2: NVDA | C2: UW | D2: =_xlfn.XLOOKUP(C2,'Exchange Code Lookup'!E:E,'Exchange Code Lookup'!F:F,"Not found") -> NASDAQ GS | E2: =_xlfn.XLOOKUP(C2,'Exchange Code Lookup'!E:E,'Exchange Code Lookup'!A:A,"Not found") -> XNGS | F2: =_xlfn.XLOOKUP(C2,'Exchange Code Lookup'!E:E,'Exchange Code Lookup'!B:B,"Not found") -> XNAS | G2: =_xlfn.XLOOKUP(C2,'Exchange Code Lookup'!E:E,'Exchange Code Lookup'!C:C,"Not found") -> NASDAQ/NGS (GLOBAL SELECT MARKET) | H2: Equity | I2: NVIDIA Corp | J2: =_xlfn.XLOOKUP(C2,'Exchange Code Lookup'!E:E,'Exchange Code Lookup'!H:H,"Not found") -> US | K2: 4.597839 | L2: 23276.336 | M2: 239.24
A3: AAPL UW Equity | B3: AAPL | C3: UW | D3: =_xlfn.XLOOKUP(C3,'Exchange Code Lookup'!E:E,'Exchange Code Lookup'!F:F,"Not found") -> NASDAQ GS | E3: =_xlfn.XLOOKUP(C3,'Exchange Code Lookup'!E:E,'Exchange Code Lookup'!A:A,"Not found") -> XNGS | F3: =_xlfn.XLOOKUP(C3,'Exchange Code Lookup'!E:E,'Exchange Code Lookup'!B:B,"Not found") -> XNAS | G3: =_xlfn.XLOOKUP(C3,'Exchange Code Lookup'!E:E,'Exchange Code Lookup'!C:C,"Not found") -> NASDAQ/NGS (GLOBAL SELECT MARKET) | H3: Equity | I3: Apple Inc | J3: =_xlfn.XLOOKUP(C3,'Exchange Code Lookup'!E:E,'Exchange Code Lookup'!H:H,"Not found") -> US | K3: 3.964919 | L3: 14393.417 | M3: 333.63
A4: MSFT UW Equity | B4: MSFT | C4: UW | D4: =_xlfn.XLOOKUP(C4,'Exchange Code Lookup'!E:E,'Exchange Code Lookup'!F:F,"Not found") -> NASDAQ GS | E4: =_xlfn.XLOOKUP(C4,'Exchange Code Lookup'!E:E,'Exchange Code Lookup'!A:A,"Not found") -> XNGS | F4: =_xlfn.XLOOKUP(C4,'Exchange Code Lookup'!E:E,'Exchange Code Lookup'!B:B,"Not found") -> XNAS | G4: =_xlfn.XLOOKUP(C4,'Exchange Code Lookup'!E:E,'Exchange Code Lookup'!C:C,"Not found") -> NASDAQ/NGS (GLOBAL SELECT MARKET) | H4: Equity | I4: Microsoft Corp | J4: =_xlfn.XLOOKUP(C4,'Exchange Code Lookup'!E:E,'Exchange Code Lookup'!H:H,"Not found") -> US | K4: 3.244055 | L4: 7423.026 | M4: 529.3
A5: AMZN UW Equity | B5: AMZN | C5: UW | D5: =_xlfn.XLOOKUP(C5,'Exchange Code Lookup'!E:E,'Exchange Code Lookup'!F:F,"Not found") -> NASDAQ GS | E5: =_xlfn.XLOOKUP(C5,'Exchange Code Lookup'!E:E,'Exchange Code Lookup'!A:A,"Not found") -> XNGS | F5: =_xlfn.XLOOKUP(C5,'Exchange Code Lookup'!E:E,'Exchange Code Lookup'!B:B,"Not found") -> XNAS | G5: =_xlfn.XLOOKUP(C5,'Exchange Code Lookup'!E:E,'Exchange Code Lookup'!C:C,"Not found") -> NASDAQ/NGS (GLOBAL SELECT MARKET) | H5: Equity | I5: Amazon.com Inc | J5: =_xlfn.XLOOKUP(C5,'Exchange Code Lookup'!E:E,'Exchange Code Lookup'!H:H,"Not found") -> US | K5: 2.088672 | L5: 9870.364 | M5: 256.29
A6: GOOGL UW Equity | B6: GOOGL | C6: UW | D6: =_xlfn.XLOOKUP(C6,'Exchange Code Lookup'!E:E,'Exchange Code Lookup'!F:F,"Not found") -> NASDAQ GS | E6: =_xlfn.XLOOKUP(C6,'Exchange Code Lookup'!E:E,'Exchange Code Lookup'!A:A,"Not found") -> XNGS | F6: =_xlfn.XLOOKUP(C6,'Exchange Code Lookup'!E:E,'Exchange Code Lookup'!B:B,"Not found") -> XNAS | G6: =_xlfn.XLOOKUP(C6,'Exchange Code Lookup'!E:E,'Exchange Code Lookup'!C:C,"Not found") -> NASDAQ/NGS (GLOBAL SELECT MARKET) | H6: Equity | I6: Alphabet Inc | J6: =_xlfn.XLOOKUP(C6,'Exchange Code Lookup'!E:E,'Exchange Code Lookup'!H:H,"Not found") -> US | K6: 1.66471 | L6: 5799.004 | M6: 347.68
A7: 2330 TT Equity | B7: 2330 | C7: TT | D7: =_xlfn.XLOOKUP(C7,'Exchange Code Lookup'!E:E,'Exchange Code Lookup'!F:F,"Not found") -> TAIPEI | E7: =_xlfn.XLOOKUP(C7,'Exchange Code Lookup'!E:E,'Exchange Code Lookup'!A:A,"Not found") -> ROCO | F7: =_xlfn.XLOOKUP(C7,'Exchange Code Lookup'!E:E,'Exchange Code Lookup'!B:B,"Not found") -> ROCO | G7: =_xlfn.XLOOKUP(C7,'Exchange Code Lookup'!E:E,'Exchange Code Lookup'!C:C,"Not found") -> TAIPEI EXCHANGE | H7: Equity | I7: Taiwan Semiconductor Manufactu | J7: =_xlfn.XLOOKUP(C7,'Exchange Code Lookup'!E:E,'Exchange Code Lookup'!H:H,"Not found") -> TW | K7: 1.598681 | L7: 23883.389 | M7: 2585
A8: AVGO UW Equity | B8: AVGO | C8: UW | D8: =_xlfn.XLOOKUP(C8,'Exchange Code Lookup'!E:E,'Exchange Code Lookup'!F:F,"Not found") -> NASDAQ GS | E8: =_xlfn.XLOOKUP(C8,'Exchange Code Lookup'!E:E,'Exchange Code Lookup'!A:A,"Not found") -> XNGS | F8: =_xlfn.XLOOKUP(C8,'Exchange Code Lookup'!E:E,'Exchange Code Lookup'!B:B,"Not found") -> XNAS | G8: =_xlfn.XLOOKUP(C8,'Exchange Code Lookup'!E:E,'Exchange Code Lookup'!C:C,"Not found") -> NASDAQ/NGS (GLOBAL SELECT MARKET) | H8: Equity | I8: Broadcom Inc | J8: =_xlfn.XLOOKUP(C8,'Exchange Code Lookup'!E:E,'Exchange Code Lookup'!H:H,"Not found") -> US | K8: 1.449213 | L8: 4670.448 | M8: 375.81
A9: GOOG UW Equity | B9: GOOG | C9: UW | D9: =_xlfn.XLOOKUP(C9,'Exchange Code Lookup'!E:E,'Exchange Code Lookup'!F:F,"Not found") -> NASDAQ GS | E9: =_xlfn.XLOOKUP(C9,'Exchange Code Lookup'!E:E,'Exchange Code Lookup'!A:A,"Not found") -> XNGS | F9: =_xlfn.XLOOKUP(C9,'Exchange Code Lookup'!E:E,'Exchange Code Lookup'!B:B,"Not found") -> XNAS | G9: =_xlfn.XLOOKUP(C9,'Exchange Code Lookup'!E:E,'Exchange Code Lookup'!C:C,"Not found") -> NASDAQ/NGS (GLOBAL SELECT MARKET) | H9: Equity | I9: Alphabet Inc | J9: =_xlfn.XLOOKUP(C9,'Exchange Code Lookup'!E:E,'Exchange Code Lookup'!H:H,"Not found") -> US | K9: 1.350542 | L9: 4746.79 | M9: 344.59
A10: META UW Equity | B10: META | C10: UW | D10: =_xlfn.XLOOKUP(C10,'Exchange Code Lookup'!E:E,'Exchange Code Lookup'!F:F,"Not found") -> NASDAQ GS | E10: =_xlfn.XLOOKUP(C10,'Exchange Code Lookup'!E:E,'Exchange Code Lookup'!A:A,"Not found") -> XNGS | F10: =_xlfn.XLOOKUP(C10,'Exchange Code Lookup'!E:E,'Exchange Code Lookup'!B:B,"Not found") -> XNAS | G10: =_xlfn.XLOOKUP(C10,'Exchange Code Lookup'!E:E,'Exchange Code Lookup'!C:C,"Not found") -> NASDAQ/NGS (GLOBAL SELECT MARKET) | H10: Equity | I10: Meta Platforms Inc | J10: =_xlfn.XLOOKUP(C10,'Exchange Code Lookup'!E:E,'Exchange Code Lookup'!H:H,"Not found") -> US | K10: 1.338672 | L10: 2194.294 | M10: 738.88
A11: TSLA UW Equity | B11: TSLA | C11: UW | D11: =_xlfn.XLOOKUP(C11,'Exchange Code Lookup'!E:E,'Exchange Code Lookup'!F:F,"Not found") -> NASDAQ GS | E11: =_xlfn.XLOOKUP(C11,'Exchange Code Lookup'!E:E,'Exchange Code Lookup'!A:A,"Not found") -> XNGS | F11: =_xlfn.XLOOKUP(C11,'Exchange Code Lookup'!E:E,'Exchange Code Lookup'!B:B,"Not found") -> XNAS | G11: =_xlfn.XLOOKUP(C11,'Exchange Code Lookup'!E:E,'Exchange Code Lookup'!C:C,"Not found") -> NASDAQ/NGS (GLOBAL SELECT MARKET) | H11: Equity | I11: Tesla Inc | J11: =_xlfn.XLOOKUP(C11,'Exchange Code Lookup'!E:E,'Exchange Code Lookup'!H:H,"Not found") -> US | K11: 1.110504 | L11: 3533.091 | M11: 380.68
A12: MU UW Equity | B12: MU | C12: UW | D12: =_xlfn.XLOOKUP(C12,'Exchange Code Lookup'!E:E,'Exchange Code Lookup'!F:F,"Not found") -> NASDAQ GS | E12: =_xlfn.XLOOKUP(C12,'Exchange Code Lookup'!E:E,'Exchange Code Lookup'!A:A,"Not found") -> XNGS | F12: =_xlfn.XLOOKUP(C12,'Exchange Code Lookup'!E:E,'Exchange Code Lookup'!B:B,"Not found") -> XNAS | G12: =_xlfn.XLOOKUP(C12,'Exchange Code Lookup'!E:E,'Exchange Code Lookup'!C:C,"Not found") -> NASDAQ/NGS (GLOBAL SELECT MARKET) | H12: Equity | I12: Micron Technology Inc | J12: =_xlfn.XLOOKUP(C12,'Exchange Code Lookup'!E:E,'Exchange Code Lookup'!H:H,"Not found") -> US | K12: 0.972658 | L12: 1126.694 | M12: 1045.56
A13: AMD UW Equity | B13: AMD | C13: UW | D13: =_xlfn.XLOOKUP(C13,'Exchange Code Lookup'!E:E,'Exchange Code Lookup'!F:F,"Not found") -> NASDAQ GS | E13: =_xlfn.XLOOKUP(C13,'Exchange Code Lookup'!E:E,'Exchange Code Lookup'!A:A,"Not found") -> XNGS | F13: =_xlfn.XLOOKUP(C13,'Exchange Code Lookup'!E:E,'Exchange Code Lookup'!B:B,"Not found") -> XNAS | G13: =_xlfn.XLOOKUP(C13,'Exchange Code Lookup'!E:E,'Exchange Code Lookup'!C:C,"Not found") -> NASDAQ/NGS (GLOBAL SELECT MARKET) | H13: Equity | I13: Advanced Micro Devices Inc | J13: =_xlfn.XLOOKUP(C13,'Exchange Code Lookup'!E:E,'Exchange Code Lookup'!H:H,"Not found") -> US | K13: 0.871129 | L13: 1624.619 | M13: 649.42
... A10421: AXG UR Equity | B10421: AXG | C10421: UR | D10421: =_xlfn.XLOOKUP(C10421,'Exchange Code Lookup'!E:E,'Exchange Code Lookup'!F:F,"Not found") -> NASDAQ CM | E10421: =_xlfn.XLOOKUP(C10421,'Exchange Code Lookup'!E:E,'Exchange Code Lookup'!A:A,"Not found") -> XNCM | F10421: =_xlfn.XLOOKUP(C10421,'Exchange Code Lookup'!E:E,'Exchange Code Lookup'!B:B,"Not found") -> XNAS | G10421: =_xlfn.XLOOKUP(C10421,'Exchange Code Lookup'!E:E,'Exchange Code Lookup'!C:C,"Not found") -> NASDAQ CAPITAL MARKET | H10421: Equity | I10421: Solowin Holdings | J10421: =_xlfn.XLOOKUP(C10421,'Exchange Code Lookup'!E:E,'Exchange Code Lookup'!H:H,"Not found") -> US | K10421: 6e-06 | L10421: 62.5 | M10421: 0.112

Sheet Exchange Code Lookup
A2: MIC | B2: Operating MIC | C2: MIC EXCHANGE NAME | D2: CORP EXCHANGE | E2: EQUITY EXCH CODE | F2: EQUITY EXCH NAME | G2: Composite Code | H2: ISO COUNTRY
A3: A2XX | B3: A2XX | C3: A2X | D3: A2X Markets | E3: AJ | F3: A2X STOCK EX | G3: SJ | H3: ZA
A4: APXL | B4: APXL | C4: SYDNEY STOCK EXCHANGE LIMITED | D4: NONE | E4: PF | F4: SYDNEY STOCK | G4: AU | H4: AU
A5: ARCX | B5: XNYS | C5: NYSE ARCA | D5: NYSE ARCA | E5: UP | F5: NYSE ARCA | G5: US | H5: US
A6: ASXP | B6: XASX | C6: ASX - PUREMATCH | D6: NONE | E6: AQ | F6: ASX PUREMATCH | G6: AU | H6: AU
A7: AQEU | B7: AQEU | C7: AQUIS EXCHANGE EUROPE | D7: NONE | E7: QE | F7: AQUIS - EU | G7: QE | H7: FR
A8: AQXE | B8: AQXE | C8: AQUIS EXCHNAGE PLC | D8: NONE | E8: QX | F8: AQUIS EXCHG | G8: QX | H8: GB
A9: BATE | B9: BCXE | C9: CBOE EUROPE -BXE ORDER BOOKS | D9: NONE | E9: EB | F9: CBOE BXE | G9: EB | H9: GB
A10: BATS | B10: XCBO | C10: CBOE BZX U.S. EQUITIES EXCHANGE | D10: BATS | E10: UF | F10: CBOE BZX | G10: US | H10: US
A11: BATY | B11: XCBO | C11: CBOE BYX U.S. EQUITIES EXCHANGE | D11: NONE | E11: VY | F11: CBOE BYX | G11: US | H11: US
A12: BCSE | B12: BCSE | C12: BELARUS CURRENCY AND STOCK EXCHANGE | D12: BELARUS | E12: RB | F12: BELARUS | G12: RB | H12: BY
A13: BEUE | B13: CCXE | C13: CBOE EUROPE - BXE ORDER BOOKS (NL) | D13: NONE | E13: E2 | F13: CBOE BXE EU | G13: E2 | H13: NL
... A22: BVMF | B22: BVMF | C22: BM&FBOVESPA S.A. - BOLSA DE VALORES, MERCADORIAS E FUTUROS | D22: SISBEX | E22: NONE | F22: No Exchange | G22: No Composite Code | H22: BR
D23: SAO PAULO | E23: BN | F23: B3 NIGHT | G23: BZ | H23: BR
D24: NONE | E24: BS | F24: B3 DAY | G24: BZ | H24: BR
D25: NONE | E25: BV | F25: BOVESPA OUT | G25: BZ | H25: BR
D26: RIO DE JANEIRO | E26: BR | F26: RIO DE JANER | G26: BZ | H26: BR
D27: SOMA | E27: BO | F27: B3 SOMA | G27: BZ | H27: BR
A28: CAPA | B28: CCXE | C28: CBOE EUROPE - APA (NL) | D28: NONE | E28: X2 | F28: CBOE APA EU | G28: X2 | H28: NL
A29: CBSX | B29: XCBO | C29: CBOE STOCK EXCHANGE | D29: NONE | E29: UO | F29: CBSX | G29: US | H29: US
A30: CHIA | B30: CHIA | C30: CHI-X AUSTRALIA | D30: Chi-X Australia | E30: AH | F30: CHIX AUSTRALIA | G30: AU | H30: AU
A31: CHIJ | B31: CHIJ | C31: CHI-X JAPAN | D31: NONE | E31: JI | F31: CHI-X JAPAN | G31: JP | H31: JP
A32: CHIX | B32: BCXE | C32: CBOE EUROPE - CXE ORDER BOOKS | D32: CHI-X | E32: IX | F32: CBOE CXE | G32: IX | H32: GB
D33: NONE | E33: XC | F33: CHI-X OTC | G33: EO | H33: GB
A34: CHIC | B34: CHIC | C34: CHI-X CANADA ATS | D34: NONE | E34: TX | F34: CHIX TORONTO | G34: CN | H34: CA
D35: NONE | E35: DV | F35: CHIX VENTURE | G35: CN | H35: CA
D36: NONE | E36: DL | F36: NSDQ CX CSE | G36: CN | H36: CA
A37: CEUX | B37: CCXE | C37: CBOE EUROPE - DXE ORDER BOOKS (NL) | D37: NONE | E37: I2 | F37: CBOE DXE | G37: I2 | H37: NL
A38: DKTC | B38: DKTC | C38: DANISH AUTHORISED MARKET PLACE LTD | D38: NONE | E38: DD | F38: DANSK OTC | G38: DC | H38: DK
A39: DCSX | B39: DCSX | C39: CURACAO | D39: NONE | E39: NONE | F39: No Exchange | G39: No Composite Code | H39: CW
A40: DIFX | B40: DIFX | C40: NASDAQ DUBAI | D40: NASDAQ DUBAI | E40: DU | F40: NASDAQ DUBAI | G40: UH | H40: AE
A41: DSMD | B41: DSMD | C41: QATAR EXCHANGE | D41: QATAR | E41: QD | F41: QATAR | G41: QD | H41: QA
A42: ECEU | B42: ECEU | C42: TRADECHO EU APA | D42: NONE | E42: X1 | F42: TRADEECHO APA | G42: X1 | H42: NL
A43: EDGA | B43: XCBO | C43: CBOE EDGA U.S. EQUITIES EXCHANGE | D43: NONE | E43: VJ | F43: EDGA | G43: US | H43: US
A44: EDGX | B44: XCBO | C44: CBOE EDGX U.S. EQUITIES EXCHANGE | D44: NONE | E44: VK | F44: EDGX | G44: US | H44: US
A45: EMTF | B45: XLUX | C45: EURO MTF | D45: EUROMTF | E45: NONE | F45: No Exchange | G45: No Composite Code | H45: LU
A46: EBMX | B46: MTSO | C46: EBM - MTF | D46: EUROMTS | E46: NONE | F46: No Exchange | G46: No Composite Code | H46: IT
A47: ENAX | B47: ASEX | C47: ATHENS EXCHANGE ALTERNATIVE MARKET | D47: NONE | E47: AA | F47: ATHENS ALT | G47: GA | H47: GR
A48: ETLX | B48: ETLX | C48: EUROTLX | D48: EUROTLX | E48: TE | F48: EUROTLX | G48: TE | H48: IT
... A72: MATN | B72: MATN | C72: MATCH NOW | D72: NONE | E72: TR | F72: TRIACT TRNTO | G72: CN | H72: CA
D73: NONE | E73: TV | F73: TRIACT VNTRE | G73: CN | H73: CA
D74: NONE | E74: TO | F74: TRIACT CSE | G74: CN | H74: CA
A75: MCAD | B75: MTSO | C75: MTS CASH DOMESTIC - MTF | D75: MTS GREECE | E75: NONE | F75: No Exchange | G75: No Composite Code | H75: IT
D76: MTS IRELAND | E76: NONE | F76: No Exchange | G76: No Composite Code | H76: IT
D77: MTS AMSTERDAM | E77: NONE | F77: No Exchange | G77: No Composite Code | H77: IT
D78: MTS PORTUGAL | E78: NONE | F78: No Exchange | G78: No Composite Code | H78: IT
D79: MTS Austria | E79: NONE | F79: No Exchange | G79: No Composite Code | H79: IT
D80: MTS Czech Repub | E80: NONE | F80: No Exchange | G80: No Composite Code | H80: IT
D81: MTS Germany | E81: NONE | F81: No Exchange | G81: No Composite Code | H81: IT
D82: MTS Hungary | E82: NONE | F82: No Exchange | G82: No Composite Code | H82: IT
D83: MTS Isreal | E83: NONE | F83: No Exchange | G83: No Composite Code | H83: IT
D84: MTS Slovenia | E84: NONE | F84: No Exchange | G84: No Composite Code | H84: IT
D85: MTS Slovakia | E85: NONE | F85: No Exchange | G85: No Composite Code | H85: IT
D86: MTS Spain | E86: NONE | F86: No Exchange | G86: No Composite Code | H86: IT
D87: MTS Cyprus | E87: NONE | F87: No Exchange | G87: No Composite Code | H87: IT
A88: MCXX | B88: MCXX | C88: MCX STOCK EXCHANGE LTD | D88: NONE | E88: IG | F88: MCX STOCK EX | G88: IN | H88: IN
A89: MESQ | B89: XKLS | C89: ACE MARKET | D89: NONE | E89: MQ | F89: MESDAQ | G89: MQ | H89: MY
A90: MISX | B90: MISX | C90: MOSCOW EXCHANGE - ALL MARKETS | D90: MICEX | E90: RX | F90: MICEX MAIN | G90: RM | H90: RU
D91: NONE | E91: RN | F91: MICEX NMD | G91: RM | H91: RU
D92: NONE | E92: RP | F92: MICEX REPO | G92: RM | H92: RU
D93: MICEX A1 | E93: NONE | F93: No Exchange | G93: No Composite Code | H93: RU
D94: MICEX A2 | E94: NONE | F94: No Exchange | G94: No Composite Code | H94: RU
D95: MICEX B | E95: NONE | F95: No Exchange | G95: No Composite Code | H95: RU
D96: MICEX V | E96: NONE | F96: No Exchange | G96: No Composite Code | H96: RU
D97: MICEX Unlisted | E97: NONE | F97: No Exchange | G97: No Composite Code | H97: RU
D98: MOEX LEVEL 1 | E98: NONE | F98: No Exchange | G98: No Composite Code | H98: RU
D99: MOEX LEVEL 2 | E99: NONE | F99: No Exchange | G99: No Composite Code | H99: RU
D100: MOEX LEVEL 3 | E100: NONE | F100: No Exchange | G100: No Composite Code | H100: RU
D101: MICEX D | E101: NONE | F101: No Exchange | G101: No Composite Code | H101: RU
A102: MOTX | B102: XMIL | C102: ELECTRONIC BOND MARKET | D102: MOT | E102: NONE | F102: No Exchange | G102: No Composite Code | H102: IT
A103: MSAX | B103: MSAX | C103: MORGAN STANLEY MTF - PERIODIC AUCTION | D103: NONE | E103: M0 | F103: MS MTF | G103: M0 | H103: FR
A104: MTAA | B104: XMIL | C104: ELECTRONIC SHARE MARKET | D104: MILAN | E104: IM | F104: BRSAITALIANA | G104: IM | H104: IT
D105: NONE | E105: IC | F105: MIL COMP DAY | G105: IM | H105: IT
D106: NONE | E106: XI | F106: BORSAITALOTC | G106: EO | H106: IT
A107: MTAH | B107: XMIL | C107: BORSA ITALIANA EQUITY MTF | D107: NONE | E107: IF | F107: MIL AFTR HRS | G107: IM | H107: IT
A108: MTCH | B108: XPAR | C108: BONDMATCH | D108: NYSE BONDMATCH | E108: NONE | F108: No Exchange | G108: No Composite Code | H108: FR
A109: MTSC | B109: MTSO | C109: MTS ITALIA | D109: MTS S.p.A. | E109: NONE | F109: No Exchange | G109: No Composite Code | H109: IT
A110: MTSD | B110: BEAM | C110: MTS DENMARK | D110: MTS DENMARK | E110: NONE | F110: No Exchange | G110: No Composite Code | H110: BE
A111: MTSF | B111: BEAM | C111: MTS FINLAND | D111: MTS Finland | E111: NONE | F111: No Exchange | G111: No Composite Code | H111: BE
A112: WMTF | B112: XWAR | C112: MTS POLAND | D112: NONE | E112: PD | F112: POLAND OTC | G112: PW | H112: PL
A113: PLUS | B113: PLUS | C113: BOERSE MUENCHEN - FREIVERKEHR | D113: NONE | E113: PG | F113: PLUS EUROPE | G113: PG | H113: DE
A114: MUND | B114: XMUN | C114: BOERSE MUENCHEN – GETTEX – FREIVERKEHR | D114: NONE | E114: GZ | F114: GETTEX | G114: GZ | H114: DE
A115: NASX | B115: NASX | C115: NASD OTC MARKET | D115: NONE | E115: NJ | F115: NIGERIA NOTC | G115: NL | H115: NG
A116: NEOE | B116: NEOE | C116: AEQUITAS NEO EXCHANGE | D116: AEQUITAS NEO LIT | E116: QF | F116: NEO-L LIT | G116: CN | H116: CA
D117: NONE | E117: QH | F117: NEO-N NEO | G117: CN | H117: CA
D118: NONE | E118: QG | F118: NEO-D DARK | G118: CN | H118: CA
A119: NILX | B119: NILX | C119: NILE STOCK EXCHANGE | D119: NONE | E119: EI | F119: NILEX | G119: EY | H119: EG
A120: NOTC | B120: NOTC | C120: NORWEGIAN OVER THE COUNTER MARKET | D120: NONE | E120: NS | F120: NORWAY OTC | G120: NO | H120: NO
A121: OMGA | B121: OMGA | C121: OMEGA ATS | D121: OMEGA CANADA ATS | E121: TG | F121: OMEGA | G121: CN | H121: CA
A122: OOTC | B122: FINR | C122: OTC BULLETIN BOARD - OTHER OTC | D122: OTC | E122: UV | F122: OTC US | G122: US | H122: US
A123: PDEX | B123: PDEX | C123: PHILIPPINE DEALING AND EXCHANGE CORP | D123: PDEx | E123: NONE | F123: No Exchange | G123: No Composite Code | H123: PH
A124: PFTS | B124: PFTS | C124: PFTS STOCK EXCHANGE | D124: PFTS | E124: UZ | F124: PFTS | G124: UZ | H124: UA
A125: PFTQ | B125: PFTS | C125: PFTS QUOTE DRIVEN | D125: NONE | E125: QU | F125: PFTSQUOTEDRV | G125: UZ | H125: UA
A126: OTCM | B126: OTCM | C126: OTC PINK MARKETPLACE | D126: PINK SHEETS | E126: PQ | F126: OTC MARKETS | G126: US | H126: US
A127: PURE | B127: XCNQ | C127: PURE TRADING | D127: PURE TRADING | E127: CJ | F127: PURE TRADING | G127: CN | H127: CA
A128: ROCO | B128: ROCO | C128: TAIPEI EXCHANGE | D128: Taipei | E128: TT | F128: TAIPEI | G128: TT | H128: TW
A129: ROTC | B129: ROTC | C129: RWANDA OTC MARKET | D129: RWANDA | E129: RW | F129: RWANDA | G129: RW | H129: RW
A130: RTSX | B130: MISX | C130: MOSCOW EXCHANGE - DERIVATIVES MARKET | D130: RUSSIAN TRADING | E130: RR | F130: MOEX | G130: RU | H130: RU
... A153: XATS | B153: XATS | C153: ALPHA EXCHANGE | D153: NONE | E153: TN | F153: ALPHAVENTURE | G153: CN | H153: CA
D154: NONE | E154: TA | F154: ALPHATORONTO | G154: CN | H154: CA
...
